neolinearalgebra/Matrix.py
neolinearalgebra/__init__.py
neolinearalgebra-0.2.4.dist-info/LICENSE
neolinearalgebra-0.2.4.dist-info/METADATA
neolinearalgebra-0.2.4.dist-info/WHEEL
neolinearalgebra-0.2.4.dist-info/top_level.txt
neolinearalgebra-0.2.4.dist-info/RECORD
