Metadata-Version: 2.1
Name: neolinearalgebra
Version: 0.2.4
Summary: NEO Linear Algebra package for Matrix Manipulation.
Home-page: https://sajidsarker.github.io/2022/09/10/neo-linear-algebra-for-python.html
Author: Sajid Sarker
Author-email: sajid.sarker@gmail.com
License: MIT
Keywords: linear algebra matrix vector math
Classifier: Development Status :: 4 - Beta
Classifier: Topic :: Utilities
Classifier: License :: OSI Approved :: MIT License
Classifier: Natural Language :: English
Classifier: Programming Language :: Python :: 3
License-File: LICENSE
